mdbsession/__init__.py
mdbsession/session.py
t/__init__.py
t/test_session.py
django_mdbsessions-0.0.2.dist-info/LICENSE
django_mdbsessions-0.0.2.dist-info/METADATA
django_mdbsessions-0.0.2.dist-info/WHEEL
django_mdbsessions-0.0.2.dist-info/top_level.txt
django_mdbsessions-0.0.2.dist-info/RECORD
