Metadata-Version: 2.1
Name: django-mdbsessions
Version: 0.0.2
Summary: Use MongoDB as Django session backend
Home-page: https://github.com/somatoko/django-mdbsessions
Author: somatoko
Author-email: 
License: MIT
Keywords: django mongodb session
Platform: UNKNOWN
Classifier: Development Status :: 3 - Alpha
Classifier: Intended Audience :: Developers
Classifier: Topic :: Internet :: WWW/HTTP :: Session
Classifier: License :: OSI Approved :: MIT License
Classifier: Programming Language :: Python :: 3.6
Requires-Dist: django (>=1.11)
Requires-Dist: pymongo (>=3.2.2)
